ai_cli/__init__.py
ai_cli/chat.py
ai_cli/cli.py
ai_cli/config.py
ai_cli/py.typed
ai_cli/shell_executor.py
ai_cli/tools/__init__.py
ai_cli/tools/base.py
ai_cli/tools/copy_file.py
ai_cli/tools/create_file.py
ai_cli/tools/create_folder.py
ai_cli/tools/dangerous.py
ai_cli/tools/move_file.py
ai_cli/tools/remove.py
ai_cli/tools/rename.py
ai_cli/tools/search_file.py
ai_cli/utils/__init__.py
ai_cli/utils/helpers.py
ai_shell_assistant-0.2.1.dist-info/licenses/LICENSE
ai_shell_assistant-0.2.1.dist-info/METADATA
ai_shell_assistant-0.2.1.dist-info/WHEEL
ai_shell_assistant-0.2.1.dist-info/entry_points.txt
ai_shell_assistant-0.2.1.dist-info/top_level.txt
ai_shell_assistant-0.2.1.dist-info/RECORD
