Metadata-Version: 2.4
Name: ai-shell-assistant
Version: 0.2.1
Summary: AI-powered command-line interface with extensible tools
Home-page: https://github.com/PierrunoYT/ai-shell-assistant
Author: PierrunoYT
Author-email: PierrunoYT <pierrebruno@hotmail.ch>
Maintainer-email: PierrunoYT <pierrebruno@hotmail.ch>
License: MIT
Project-URL: Homepage, https://github.com/PierrunoYT/ai-shell-assistant
Project-URL: Documentation, https://github.com/PierrunoYT/ai-shell-assistant#readme
Project-URL: Repository, https://github.com/PierrunoYT/ai-shell-assistant
Project-URL: Bug Tracker, https://github.com/PierrunoYT/ai-shell-assistant/issues
Keywords: ai,cli,shell,assistant,openai,gpt,command-line,natural-language,automation,tools,file-operations
Classifier: Development Status :: 4 - Beta
Classifier: Intended Audience :: Developers
Classifier: Intended Audience :: System Administrators
Classifier: License :: OSI Approved :: MIT License
Classifier: Operating System :: OS Independent
Classifier: Programming Language :: Python :: 3
Classifier: Programming Language :: Python :: 3.8
Classifier: Programming Language :: Python :: 3.9
Classifier: Programming Language :: Python :: 3.10
Classifier: Programming Language :: Python :: 3.11
Classifier: Programming Language :: Python :: 3.12
Classifier: Topic :: Software Development :: Libraries :: Python Modules
Classifier: Topic :: System :: Shells
Classifier: Topic :: Utilities
Classifier: Environment :: Console
Requires-Python: >=3.8
License-File: LICENSE
Requires-Dist: openai>=1.0.0
Requires-Dist: python-dotenv>=1.0.0
Requires-Dist: requests>=2.31.0
Requires-Dist: click>=8.1.7
Requires-Dist: rich>=13.5.0
Requires-Dist: pydantic>=2.4.0
Provides-Extra: dev
Requires-Dist: pytest>=7.0.0; extra == "dev"
Requires-Dist: pytest-cov>=4.0.0; extra == "dev"
Requires-Dist: black>=23.0.0; extra == "dev"
Requires-Dist: flake8>=6.0.0; extra == "dev"
Requires-Dist: mypy>=1.0.0; extra == "dev"
Requires-Dist: pre-commit>=3.0.0; extra == "dev"
Dynamic: author
Dynamic: home-page
Dynamic: license-file
Dynamic: requires-python
